openlatestscreenshot/__init__.py
openlatestscreenshot/__version__.py
openlatestscreenshot/linux.py
openlatestscreenshot/script.py
openlatestscreenshot/scripts/gnome-notification.sh
openlatestscreenshot/util.py
openlatestscreenshot/windows.py
openlatestscreenshot-0.3.1.dist-info/WHEEL
openlatestscreenshot-0.3.1.dist-info/entry_points.txt
openlatestscreenshot-0.3.1.dist-info/METADATA
openlatestscreenshot-0.3.1.dist-info/RECORD
