Metadata-Version: 2.4
Name: openlatestscreenshot
Version: 0.3.1
Summary: Open the latest screenshot you took in your default image viewer
Author: DrTexx
Author-email: DrTexx <denver.opensource@tutanota.com>
License-Expression: AGPL-3.0-only
Requires-Python: >=3.10
